pywe_membercard/__init__.py
pywe_membercard/pywemembercard.py
pywe_membercard-1.0.4.dist-info/METADATA
pywe_membercard-1.0.4.dist-info/WHEEL
pywe_membercard-1.0.4.dist-info/top_level.txt
pywe_membercard-1.0.4.dist-info/RECORD
